py_trees/__init__.py
py_trees/behaviour.py
py_trees/behaviours.py
py_trees/blackboard.py
py_trees/common.py
py_trees/composites.py
py_trees/console.py
py_trees/decorators.py
py_trees/demos/README.md
py_trees/demos/__init__.py
py_trees/demos/action.py
py_trees/demos/blackboard.py
py_trees/demos/blackboard_namespaces.py
py_trees/demos/blackboard_remappings.py
py_trees/demos/context_switching.py
py_trees/demos/display_modes.py
py_trees/demos/dot_graphs.py
py_trees/demos/either_or.py
py_trees/demos/eternal_guard.py
py_trees/demos/lifecycle.py
py_trees/demos/logging.py
py_trees/demos/pick_up_where_you_left_off.py
py_trees/demos/selector.py
py_trees/demos/sequence.py
py_trees/demos/stewardship.py
py_trees/display.py
py_trees/idioms.py
py_trees/logging.py
py_trees/meta.py
py_trees/programs/__init__.py
py_trees/programs/render.py
py_trees/py.typed
py_trees/syntax_highlighting.py
py_trees/tests.py
py_trees/timers.py
py_trees/trees.py
py_trees/utilities.py
py_trees/version.py
py_trees/visitors.py
py_trees-2.2.2.dist-info/LICENSE
py_trees-2.2.2.dist-info/WHEEL
py_trees-2.2.2.dist-info/entry_points.txt
py_trees-2.2.2.dist-info/METADATA
py_trees-2.2.2.dist-info/RECORD
