Metadata-Version: 2.1
Name: py-trees
Version: 2.2.2
Summary: pythonic implementation of behaviour trees
Home-page: https://github.com/splintered-reality/py_trees
License: BSD
Keywords: py_trees,py-trees,behaviour-trees
Author: Daniel Stonier
Maintainer: Daniel Stonier
Maintainer-email: d.stonier@gmail.com
Requires-Python: >=3.8,<4.0
Classifier: Environment :: Console
Classifier: Intended Audience :: Developers
Classifier: License :: OSI Approved :: BSD License
Classifier: License :: Other/Proprietary License
Classifier: Programming Language :: Python
Classifier: Programming Language :: Python :: 3
Classifier: Programming Language :: Python :: 3.8
Classifier: Programming Language :: Python :: 3.9
Classifier: Programming Language :: Python :: 3.10
Classifier: Programming Language :: Python :: 3.11
Classifier: Topic :: Scientific/Engineering :: Artificial Intelligence
Classifier: Topic :: Software Development :: Libraries
Requires-Dist: pydot (>=1.4)
Project-URL: Documentation, https://py-trees.readthedocs.io/en/devel/
Project-URL: Repository, https://github.com/splintered-reality/py_trees
